code/__init__.py
code/pytoplot.py
code/pyxrdspec.py
cosstools/__init__.py
cosstools/hellocoss.py
cosstools/hellocry.py
cosstools/pytoplot.py
cosstools/pyxrdspec.py
cosstools-1.3.0.dist-info/METADATA
cosstools-1.3.0.dist-info/WHEEL
cosstools-1.3.0.dist-info/top_level.txt
cosstools-1.3.0.dist-info/RECORD
