Metadata-Version: 2.1
Name: cosstools
Version: 1.3.0
Summary: Python tools by Alessandro Cossard for the CRYSTAL software
Home-page: UNKNOWN
Author: Alessandro Cossard
Author-email: <alessandro.cossard@unito.it>
License: UNKNOWN
Keywords: python,chemistry,physics,crystal,topond,quantum
Platform: UNKNOWN
Classifier: Development Status :: 1 - Planning
Classifier: Intended Audience :: Developers
Classifier: Programming Language :: Python :: 3
Classifier: Operating System :: Unix
Classifier: Operating System :: MacOS :: MacOS X
Classifier: Operating System :: Microsoft :: Windows
